sphinxcontrib_text_styles/__init__.py
sphinxcontrib_text_styles/formatting.py
sphinxcontrib_text_styles-0.2.1.dist-info/licenses/LICENSE
sphinxcontrib_text_styles-0.2.1.dist-info/METADATA
sphinxcontrib_text_styles-0.2.1.dist-info/WHEEL
sphinxcontrib_text_styles-0.2.1.dist-info/entry_points.txt
sphinxcontrib_text_styles-0.2.1.dist-info/top_level.txt
sphinxcontrib_text_styles-0.2.1.dist-info/RECORD
