Metadata-Version: 2.4
Name: sphinxcontrib-text-styles
Version: 0.2.1
Summary: Sphinx extension for custom text formatting roles
Author: Martin Priestley
License-Expression: MIT
Project-URL: Homepage, https://github.com/martinpriestley/sphinxcontrib-text-styles
Keywords: sphinx,extension,formatting,documentation
Classifier: Development Status :: 3 - Alpha
Classifier: Framework :: Sphinx :: Extension
Classifier: Intended Audience :: Developers
Classifier: Programming Language :: Python :: 3
Requires-Python: >=3.7
License-File: LICENSE
Requires-Dist: sphinx>=6.0
Dynamic: license-file
